enformer_pytorch/__init__.py
enformer_pytorch/config_enformer.py
enformer_pytorch/data.py
enformer_pytorch/finetune.py
enformer_pytorch/metrics.py
enformer_pytorch/modeling_enformer.py
enformer_pytorch/precomputed/tf_gammas.pt
enformer_pytorch-0.8.11.dist-info/licenses/LICENSE
enformer_pytorch-0.8.11.dist-info/METADATA
enformer_pytorch-0.8.11.dist-info/WHEEL
enformer_pytorch-0.8.11.dist-info/top_level.txt
enformer_pytorch-0.8.11.dist-info/RECORD
