Metadata-Version: 2.4
Name: enformer-pytorch
Version: 0.8.11
Summary: Enformer - Pytorch
Home-page: https://github.com/lucidrains/enformer-pytorch
Author: Phil Wang
Author-email: lucidrains@gmail.com
License: MIT
Keywords: artificial intelligence,transformer,gene-expression
Classifier: Development Status :: 4 - Beta
Classifier: Intended Audience :: Developers
Classifier: Topic :: Scientific/Engineering :: Artificial Intelligence
Classifier: License :: OSI Approved :: MIT License
Classifier: Programming Language :: Python :: 3.6
License-File: LICENSE
Requires-Dist: discrete-key-value-bottleneck-pytorch>=0.0.8
Requires-Dist: einops>=0.3
Requires-Dist: numpy>=2.3.1
Requires-Dist: torch>=1.6
Requires-Dist: torchmetrics
Requires-Dist: polars
Requires-Dist: pyfaidx
Requires-Dist: pyyaml
Requires-Dist: transformers[torch]
Dynamic: author
Dynamic: author-email
Dynamic: classifier
Dynamic: description-content-type
Dynamic: home-page
Dynamic: keywords
Dynamic: license
Dynamic: license-file
Dynamic: requires-dist
Dynamic: summary
